figurex/__init__.py
figurex/basemap.py
figurex/cartopy.py
figurex/figure.py
figurex-0.2.15.dist-info/licenses/LICENSE
figurex-0.2.15.dist-info/METADATA
figurex-0.2.15.dist-info/WHEEL
figurex-0.2.15.dist-info/top_level.txt
figurex-0.2.15.dist-info/RECORD
